README.txt
setup.py
redirectall/__init__.py
redirectall/dispatcher.py
redirectall/factory.py
redirectall.egg-info/PKG-INFO
redirectall.egg-info/SOURCES.txt
redirectall.egg-info/dependency_links.txt
redirectall.egg-info/entry_points.txt
redirectall.egg-info/not-zip-safe
redirectall.egg-info/requires.txt
redirectall.egg-info/top_level.txt