Metadata-Version: 1.0
Name: redirectall
Version: 0.0
Summary: redirect all traffic as moved permanantly
Home-page: http://k0s.org/hg/redirector
Author: Jeff Hammel
Author-email: jhammel@mozilla.com
License: MPL
Platform: UNKNOWN
